ucumvert/__init__.py
ucumvert/_version.py
ucumvert/cli.py
ucumvert/parser.py
ucumvert/pint_ucum_defs.txt
ucumvert/pint_ucum_defs_mapping_report.txt
ucumvert/ucum_grammar.lark
ucumvert/ucum_pint.py
ucumvert/xml_util.py
ucumvert/vendor/README.md
ucumvert/vendor/get_ucum_example_as_tsv.py
ucumvert/vendor/ucum-essence.xml
ucumvert/vendor/ucum_examples.tsv
ucumvert-0.3.0.dist-info/METADATA
ucumvert-0.3.0.dist-info/WHEEL
ucumvert-0.3.0.dist-info/entry_points.txt
ucumvert-0.3.0.dist-info/licenses/LICENSE
ucumvert-0.3.0.dist-info/RECORD
