Metadata-Version: 2.4
Name: ucumvert
Version: 0.3.0
Summary: Python parser & interface for UCUM (Unified Code for Units of Measure).
Project-URL: Documentation, https://github.com/dalito/ucumvert
Project-URL: GitHub, https://github.com/dalito/ucumvert
Project-URL: Changelog, https://github.com/dalito/ucumvert/releases
Author-email: David Linke <david.linke@catalysis.de>
Maintainer-email: David Linke <david.linke@catalysis.de>
License-Expression: MIT
License-File: LICENSE
Keywords: UCUM,parser,units of measurement
Classifier: Development Status :: 4 - Beta
Classifier: Environment :: Console
Classifier: Intended Audience :: Science/Research
Classifier: Operating System :: OS Independent
Classifier: Programming Language :: Python
Classifier: Programming Language :: Python :: 3.11
Classifier: Programming Language :: Python :: 3.12
Classifier: Programming Language :: Python :: 3.13
Classifier: Programming Language :: Python :: 3.14
Requires-Python: >=3.9
Requires-Dist: lark
Requires-Dist: pint>=0.25.0
Provides-Extra: dev
Requires-Dist: coverage; extra == 'dev'
Requires-Dist: openpyxl; extra == 'dev'
Requires-Dist: pydot; extra == 'dev'
Requires-Dist: pytest; extra == 'dev'
Requires-Dist: ruff; extra == 'dev'
Provides-Extra: lint
Requires-Dist: ruff; extra == 'lint'
Provides-Extra: tests
Requires-Dist: coverage; extra == 'tests'
Requires-Dist: pytest; extra == 'tests'
